rlax/__init__.py
rlax/rlax_test.py
rlax/_src/__init__.py
rlax/_src/base.py
rlax/_src/base_test.py
rlax/_src/clipping.py
rlax/_src/clipping_test.py
rlax/_src/distributions.py
rlax/_src/distributions_test.py
rlax/_src/embedding.py
rlax/_src/embedding_test.py
rlax/_src/episodic_memory.py
rlax/_src/episodic_memory_test.py
rlax/_src/exploration.py
rlax/_src/exploration_test.py
rlax/_src/general_value_functions.py
rlax/_src/general_value_functions_test.py
rlax/_src/interruptions.py
rlax/_src/interruptions_test.py
rlax/_src/losses.py
rlax/_src/losses_test.py
rlax/_src/model_learning.py
rlax/_src/model_learning_test.py
rlax/_src/moving_averages.py
rlax/_src/moving_averages_test.py
rlax/_src/mpo_ops.py
rlax/_src/mpo_ops_test.py
rlax/_src/multistep.py
rlax/_src/multistep_test.py
rlax/_src/nested_updates.py
rlax/_src/nested_updates_test.py
rlax/_src/nonlinear_bellman.py
rlax/_src/nonlinear_bellman_test.py
rlax/_src/policy_gradients.py
rlax/_src/policy_gradients_test.py
rlax/_src/policy_targets.py
rlax/_src/policy_targets_test.py
rlax/_src/pop_art.py
rlax/_src/pop_art_test.py
rlax/_src/test_utils.py
rlax/_src/transforms.py
rlax/_src/transforms_test.py
rlax/_src/tree_util.py
rlax/_src/tree_util_test.py
rlax/_src/value_learning.py
rlax/_src/value_learning_test.py
rlax/_src/vtrace.py
rlax/_src/vtrace_test.py
rlax-0.1.8.dist-info/licenses/LICENSE
rlax-0.1.8.dist-info/WHEEL
rlax-0.1.8.dist-info/METADATA
rlax-0.1.8.dist-info/RECORD
