Metadata-Version: 2.4
Name: rlax
Version: 0.1.8
Summary: A library of reinforcement learning building blocks in JAX.
Keywords: reinforcement-learning,python,machine learning
Author-email: Google DeepMind <rlax-dev@google.com>
Requires-Python: >=3.11
Classifier: Environment :: Console
Classifier: Programming Language :: Python
Classifier: Intended Audience :: Developers
Classifier: Operating System :: OS Independent
Classifier: Programming Language :: Python :: 3
Classifier: Intended Audience :: Science/Research
Classifier: Development Status :: 4 - Beta
Classifier: License :: OSI Approved :: Apache Software License
Classifier: Topic :: Scientific/Engineering :: Artificial Intelligence
Classifier: Topic :: Software Development :: Libraries :: Python Modules
License-File: LICENSE
Requires-Dist: absl-py>=2.3.1
Requires-Dist: chex>=0.1.90
Requires-Dist: distrax>=0.1.7
Requires-Dist: dm_env>=1.6
Requires-Dist: jax>=0.7.0
Requires-Dist: jaxlib>=0.7.0
Requires-Dist: numpy>=1.24.1
Requires-Dist: sphinx>=6.0.0 ; extra == "docs"
Requires-Dist: sphinx-book-theme>=1.0.1 ; extra == "docs"
Requires-Dist: sphinxcontrib-katex ; extra == "docs"
Requires-Dist: dm-haiku>=0.0.14 ; extra == "test"
Requires-Dist: flax>=0.5.3 ; extra == "test"
Requires-Dist: optax>=0.2.5 ; extra == "test"
Project-URL: homepage, https://github.com/google-deepmind/rlax
Project-URL: repository, https://github.com/google-deepmind/rlax
Provides-Extra: docs
Provides-Extra: test
